odoo/addons/mrp_account_analytic/README.rst
odoo/addons/mrp_account_analytic/__init__.py
odoo/addons/mrp_account_analytic/__manifest__.py
odoo/addons/mrp_account_analytic/i18n/es.po
odoo/addons/mrp_account_analytic/i18n/es_CO.po
odoo/addons/mrp_account_analytic/i18n/hr.po
odoo/addons/mrp_account_analytic/i18n/it.po
odoo/addons/mrp_account_analytic/i18n/mrp_account_analytic.pot
odoo/addons/mrp_account_analytic/models/__init__.py
odoo/addons/mrp_account_analytic/models/account_analytic_line.py
odoo/addons/mrp_account_analytic/models/mrp_workorder.py
odoo/addons/mrp_account_analytic/models/stock_move.py
odoo/addons/mrp_account_analytic/readme/CONTRIBUTORS.rst
odoo/addons/mrp_account_analytic/readme/DESCRIPTION.rst
odoo/addons/mrp_account_analytic/readme/USAGE.rst
odoo/addons/mrp_account_analytic/static/description/icon.png
odoo/addons/mrp_account_analytic/static/description/index.html
odoo/addons/mrp_account_analytic/tests/__init__.py
odoo/addons/mrp_account_analytic/tests/test_mrp_analytic.py
odoo/addons/mrp_account_analytic/views/account_analytic_line_view.xml
odoo_addon_mrp_account_analytic-15.0.1.0.2.2.dist-info/METADATA
odoo_addon_mrp_account_analytic-15.0.1.0.2.2.dist-info/WHEEL
odoo_addon_mrp_account_analytic-15.0.1.0.2.2.dist-info/top_level.txt
odoo_addon_mrp_account_analytic-15.0.1.0.2.2.dist-info/RECORD
